{
  "naicsCode": "493120",
  "marketName": "Refrigerated Warehousing and Storage",
  "slug": "refrigerated_warehousing",
  "alternatives": [
    {
      "id": "A1",
      "name": "Multi-MWh Li-ion BESS EPC",
      "unspsc": "",
      "tradeoffs": "['CAPEX €250-400/kWh', 'thermal-runaway risk', '6-12 mo cert lead', 'MV grid required']",
      "category": "same_category_same_outcome",
      "existential": false
    },
    {
      "id": "A2",
      "name": "Diesel/gas standby genset only",
      "unspsc": "",
      "tradeoffs": "['diesel cost & CO2', '60-120 s start delay', 'no peak-shave revenue', 'BImSchV emission limits']",
      "category": "different_approach",
      "existential": false
    },
    {
      "id": "A3",
      "name": "DSO grid-capacity upgrade",
      "unspsc": "",
      "tradeoffs": "['1-3 yr DSO lead', 'may be denied in saturated feeders', 'no resilience benefit', 'recurring Netzentgelte']",
      "category": "workaround",
      "existential": false
    },
    {
      "id": "A4",
      "name": "Behind-the-meter PV + minimal storage",
      "unspsc": "",
      "tradeoffs": "['cannot cover 24/7 reefer baseload', 'intermittent', 'weather-dependent', 'no real peak-shave headroom']",
      "category": "different_category_same_outcome",
      "existential": false
    },
    {
      "id": "A5",
      "name": "Do nothing — pay demand charges & accept outage risk",
      "unspsc": "",
      "tradeoffs": "['zero capex', '60-440 €/kW/yr Leistungspreis recurring', 'uninsured spoilage exposure']",
      "category": "status_quo",
      "existential": true
    }
  ]
}