{
  "slug": "wind_power_generation",
  "marketName": "Wind Electric Power Generation",
  "naicsCode": "221115",
  "outputTypes": [
    {
      "id": "wtg_onshore",
      "name": "Wind Turbine Generator (onshore 3–8 MW)",
      "notes": "end_product",
      "focalCompanyPresent": false
    },
    {
      "id": "bess_colocated",
      "name": "Battery Energy Storage System (≥1 MWh, MV-coupled)",
      "notes": "vn_system",
      "focalCompanyPresent": true
    }
  ],
  "focalCompany": {
    "name": "Mein Solar GmbH",
    "product": "EPC für Großbatteriespeicher",
    "bomPositionLevel": "",
    "positionRationale": ""
  },
  "productAnchorIds": [],
  "l4Subsystems": [
    {
      "id": "Rotor subsystem",
      "name": "Rotor subsystem",
      "description": "Capture kinetic energy",
      "costSharePct": 20,
      "isProductAnchor": false,
      "bomId": "wtg_onshore",
      "l3Modules": []
    },
    {
      "id": "Nacelle subsystem",
      "name": "Nacelle subsystem",
      "description": "Convert rotation to electricity",
      "costSharePct": 25,
      "isProductAnchor": false,
      "bomId": "wtg_onshore",
      "l3Modules": []
    },
    {
      "id": "Tower subsystem",
      "name": "Tower subsystem",
      "description": "Elevate rotor to wind resource",
      "costSharePct": 45,
      "isProductAnchor": false,
      "bomId": "wtg_onshore",
      "l3Modules": []
    },
    {
      "id": "Electrical & control subsystem",
      "name": "Electrical & control subsystem",
      "description": "Power conditioning + grid interface",
      "costSharePct": 5,
      "isProductAnchor": false,
      "bomId": "wtg_onshore",
      "l3Modules": []
    },
    {
      "id": "Foundation & BoP subsystem",
      "name": "Foundation & BoP subsystem",
      "description": "Anchor + interconnect",
      "costSharePct": 5,
      "isProductAnchor": false,
      "bomId": "wtg_onshore",
      "l3Modules": []
    },
    {
      "id": "Battery subsystem",
      "name": "Battery subsystem",
      "description": "Store and release charge",
      "costSharePct": null,
      "isProductAnchor": false,
      "bomId": "bess_colocated",
      "l3Modules": []
    },
    {
      "id": "Power conversion subsystem (PCS)",
      "name": "Power conversion subsystem (PCS)",
      "description": "DC↔AC bidirectional conversion",
      "costSharePct": null,
      "isProductAnchor": false,
      "bomId": "bess_colocated",
      "l3Modules": []
    },
    {
      "id": "MV grid-coupling subsystem",
      "name": "MV grid-coupling subsystem",
      "description": "10/20 kV grid interface",
      "costSharePct": null,
      "isProductAnchor": false,
      "bomId": "bess_colocated",
      "l3Modules": []
    },
    {
      "id": "Control & EMS subsystem",
      "name": "Control & EMS subsystem",
      "description": "Dispatch optimization",
      "costSharePct": null,
      "isProductAnchor": false,
      "bomId": "bess_colocated",
      "l3Modules": []
    },
    {
      "id": "Enclosure / thermal / safety subsystem",
      "name": "Enclosure / thermal / safety subsystem",
      "description": "Container + HVAC + fire suppression",
      "costSharePct": null,
      "isProductAnchor": false,
      "bomId": "bess_colocated",
      "l3Modules": []
    },
    {
      "id": "Civil & site subsystem",
      "name": "Civil & site subsystem",
      "description": "Foundation, cabling, fencing",
      "costSharePct": null,
      "isProductAnchor": false,
      "bomId": "bess_colocated",
      "l3Modules": []
    }
  ],
  "sources": []
}